torchsde/__init__.py
torchsde/settings.py
torchsde/types.py
torchsde/_brownian/__init__.py
torchsde/_brownian/brownian_base.py
torchsde/_brownian/brownian_interval.py
torchsde/_brownian/derived.py
torchsde/_core/__init__.py
torchsde/_core/adaptive_stepping.py
torchsde/_core/adjoint.py
torchsde/_core/adjoint_sde.py
torchsde/_core/base_sde.py
torchsde/_core/base_solver.py
torchsde/_core/better_abc.py
torchsde/_core/interp.py
torchsde/_core/misc.py
torchsde/_core/sdeint.py
torchsde/_core/methods/__init__.py
torchsde/_core/methods/euler.py
torchsde/_core/methods/euler_heun.py
torchsde/_core/methods/heun.py
torchsde/_core/methods/log_ode.py
torchsde/_core/methods/midpoint.py
torchsde/_core/methods/milstein.py
torchsde/_core/methods/reversible_heun.py
torchsde/_core/methods/srk.py
torchsde/_core/methods/tableaus/__init__.py
torchsde/_core/methods/tableaus/sra1.py
torchsde/_core/methods/tableaus/sra2.py
torchsde/_core/methods/tableaus/sra3.py
torchsde/_core/methods/tableaus/srid1.py
torchsde/_core/methods/tableaus/srid2.py
torchsde-0.2.6.dist-info/LICENSE
torchsde-0.2.6.dist-info/METADATA
torchsde-0.2.6.dist-info/WHEEL
torchsde-0.2.6.dist-info/top_level.txt
torchsde-0.2.6.dist-info/RECORD
