Metadata-Version: 2.1
Name: torchsde
Version: 0.2.6
Summary: SDE solvers and stochastic adjoint sensitivity analysis in PyTorch.
Home-page: https://github.com/google-research/torchsde
Author: Xuechen Li, Patrick Kidger
Author-email: lxuechen@cs.stanford.edu, hello@kidger.site
Classifier: Programming Language :: Python :: 3
Classifier: License :: OSI Approved :: Apache Software License
Requires-Python: >=3.8
License-File: LICENSE
